autoBinning/__init__.py
autoBinning/utils/__init__.py
autoBinning/utils/backwardSplit.py
autoBinning/utils/forwardSplit.py
autoBinning/utils/mapa.py
autoBinning/utils/simpleMethods.py
autoBinning/utils/trendDiscretization.py
autoBinning/utils/trendSplit.py
utils/__init__.py
utils/backwardSplit.py
utils/forwardSplit.py
utils/mapa.py
utils/simpleMethods.py
utils/trendDiscretization.py
utils/trendSplit.py
autoBinning-0.1.7.dist-info/LICENSE
autoBinning-0.1.7.dist-info/METADATA
autoBinning-0.1.7.dist-info/WHEEL
autoBinning-0.1.7.dist-info/top_level.txt
autoBinning-0.1.7.dist-info/RECORD
