Metadata-Version: 2.1
Name: autoBinning
Version: 0.1.7
Summary: A small package for feature autoBinning
Home-page: https://github.com/kaiwang0112006/autoBinning
Author: Kai Wang
Author-email: wangkai0112006@163.com
License: UNKNOWN
Platform: UNKNOWN
Classifier: Programming Language :: Python :: 3
Classifier: License :: OSI Approved :: MIT License
Classifier: Operating System :: OS Independent
Requires-Dist: numpy
Requires-Dist: scipy
